check_json/__init__.py
check_json/__main__.py
check_json-0.6.3.data/scripts/check_json
check_json-0.6.3.dist-info/LICENSE
check_json-0.6.3.dist-info/METADATA
check_json-0.6.3.dist-info/WHEEL
check_json-0.6.3.dist-info/top_level.txt
check_json-0.6.3.dist-info/RECORD
