Metadata-Version: 2.1
Name: check_json
Version: 0.6.3
Summary: A Nagios/Icinga plugin for monitoring JSON files with Jq filters
Home-page: https://gitlab.com/cspeterson/check_json
Author: Christopher Peterson
Author-email: contact@cspeterson.net
Project-URL: Bug Tracker, https://gitlab.com/cspeterson/check_json/issues
Classifier: Programming Language :: Python :: 3
Classifier: License :: OSI Approved :: MIT License
Classifier: Operating System :: OS Independent
Requires-Python: >=3.4
License-File: LICENSE
Requires-Dist: jq >=1.1.3
Requires-Dist: nagiosplugin >=1.3.2
Requires-Dist: requests >=2.27.1
